{
    "name": "flare",
    "children": [
        {
            "name": "0",
            "children": [
                {
                    "name": "svg/svg/rect",
                    "value": 1
                },
                {
                    "name": "svg/svg/rect_1",
                    "value": 1
                },
                {
                    "name": "2",
                    "children": [
                        {
                            "name": "3",
                            "children": [
                                {
                                    "name": "0",
                                    "children": [
                                        {
                                            "name": "svg/svg/g/g_4/g_5/text",
                                            "value": 1
                                        },
                                        {
                                            "name": "svg/svg/g/g_4/g_5/text_1",
                                            "value": 1
                                        },
                                        {
                                            "name": "svg/svg/g/g_4/g_5/text_2",
                                            "value": 1
                                        },
                                        {
                                            "name": "svg/svg/g/g_4/g_5/text_3",
                                            "value": 1
                                        },
                                        {
                                            "name": "svg/svg/g/g_4/g_5/text_4",
                                            "value": 1
                                        },
                                        {
                                            "name": "svg/svg/g/g_4/g_5/text_5",
                                            "value": 1
                                        },
                                        {
                                            "name": "svg/svg/g/g_4/g_5/text_6",
                                            "value": 1
                                        },
                                        {
                                            "name": "svg/svg/g/g_4/g_5/text_7",
                                            "value": 1
                                        },
                                        {
                                            "name": "svg/svg/g/g_4/g_5/text_8",
                                            "value": 1
                                        },
                                        {
                                            "name": "svg/svg/g/g_4/g_5/text_9",
                                            "value": 1
                                        },
                                        {
                                            "name": "svg/svg/g/g_4/g_5/text_10",
                                            "value": 1
                                        },
                                        {
                                            "name": "svg/svg/g/g_4/g_5/text_11",
                                            "value": 1
                                        },
                                        {
                                            "name": "svg/svg/g/g_4/g_5/text_12",
                                            "value": 1
                                        }
                                    ]
                                }
                            ]
                        },
                        {
                            "name": "svg/svg/g/line",
                            "value": 1
                        },
                        {
                            "name": "svg/svg/g/line_1",
                            "value": 1
                        },
                        {
                            "name": "6",
                            "children": [
                                {
                                    "name": "4",
                                    "children": [
                                        {
                                            "name": "0",
                                            "children": [
                                                {
                                                    "name": "0",
                                                    "children": [
                                                        {
                                                            "name": "svg/svg/g/g_6/g_11/g_12/g_13/path",
                                                            "value": 1
                                                        }
                                                    ]
                                                },
                                                {
                                                    "name": "1",
                                                    "children": [
                                                        {
                                                            "name": "svg/svg/g/g_6/g_11/g_12/g_14/path_1",
                                                            "value": 1
                                                        }
                                                    ]
                                                },
                                                {
                                                    "name": "2",
                                                    "children": [
                                                        {
                                                            "name": "svg/svg/g/g_6/g_11/g_12/g_15/path_2",
                                                            "value": 1
                                                        }
                                                    ]
                                                },
                                                {
                                                    "name": "3",
                                                    "children": [
                                                        {
                                                            "name": "svg/svg/g/g_6/g_11/g_12/g_16/path_3",
                                                            "value": 1
                                                        }
                                                    ]
                                                },
                                                {
                                                    "name": "4",
                                                    "children": [
                                                        {
                                                            "name": "svg/svg/g/g_6/g_11/g_12/g_17/path_4",
                                                            "value": 1
                                                        }
                                                    ]
                                                },
                                                {
                                                    "name": "5",
                                                    "children": [
                                                        {
                                                            "name": "svg/svg/g/g_6/g_11/g_12/g_18/path_5",
                                                            "value": 1
                                                        }
                                                    ]
                                                },
                                                {
                                                    "name": "6",
                                                    "children": [
                                                        {
                                                            "name": "svg/svg/g/g_6/g_11/g_12/g_19/path_6",
                                                            "value": 1
                                                        }
                                                    ]
                                                },
                                                {
                                                    "name": "7",
                                                    "children": [
                                                        {
                                                            "name": "svg/svg/g/g_6/g_11/g_12/g_20/path_7",
                                                            "value": 1
                                                        }
                                                    ]
                                                },
                                                {
                                                    "name": "8",
                                                    "children": [
                                                        {
                                                            "name": "svg/svg/g/g_6/g_11/g_12/g_21/path_8",
                                                            "value": 1
                                                        }
                                                    ]
                                                },
                                                {
                                                    "name": "9",
                                                    "children": [
                                                        {
                                                            "name": "svg/svg/g/g_6/g_11/g_12/g_22/path_9",
                                                            "value": 1
                                                        }
                                                    ]
                                                },
                                                {
                                                    "name": "10",
                                                    "children": [
                                                        {
                                                            "name": "svg/svg/g/g_6/g_11/g_12/g_23/path_10",
                                                            "value": 1
                                                        }
                                                    ]
                                                },
                                                {
                                                    "name": "11",
                                                    "children": [
                                                        {
                                                            "name": "svg/svg/g/g_6/g_11/g_12/g_24/path_11",
                                                            "value": 1
                                                        }
                                                    ]
                                                },
                                                {
                                                    "name": "12",
                                                    "children": [
                                                        {
                                                            "name": "svg/svg/g/g_6/g_11/g_12/g_25/path_12",
                                                            "value": 1
                                                        }
                                                    ]
                                                },
                                                {
                                                    "name": "13",
                                                    "children": [
                                                        {
                                                            "name": "svg/svg/g/g_6/g_11/g_12/g_26/path_13",
                                                            "value": 1
                                                        }
                                                    ]
                                                },
                                                {
                                                    "name": "14",
                                                    "children": [
                                                        {
                                                            "name": "svg/svg/g/g_6/g_11/g_12/g_27/path_14",
                                                            "value": 1
                                                        }
                                                    ]
                                                },
                                                {
                                                    "name": "15",
                                                    "children": [
                                                        {
                                                            "name": "svg/svg/g/g_6/g_11/g_12/g_28/path_15",
                                                            "value": 1
                                                        }
                                                    ]
                                                },
                                                {
                                                    "name": "16",
                                                    "children": [
                                                        {
                                                            "name": "svg/svg/g/g_6/g_11/g_12/g_29/path_16",
                                                            "value": 1
                                                        }
                                                    ]
                                                },
                                                {
                                                    "name": "17",
                                                    "children": [
                                                        {
                                                            "name": "svg/svg/g/g_6/g_11/g_12/g_30/path_17",
                                                            "value": 1
                                                        }
                                                    ]
                                                },
                                                {
                                                    "name": "18",
                                                    "children": [
                                                        {
                                                            "name": "svg/svg/g/g_6/g_11/g_12/g_31/path_18",
                                                            "value": 1
                                                        }
                                                    ]
                                                },
                                                {
                                                    "name": "19",
                                                    "children": [
                                                        {
                                                            "name": "svg/svg/g/g_6/g_11/g_12/g_32/path_19",
                                                            "value": 1
                                                        },
                                                        {
                                                            "name": "svg/svg/g/g_6/g_11/g_12/g_32/path_20",
                                                            "value": 1
                                                        }
                                                    ]
                                                }
                                            ]
                                        }
                                    ]
                                },
                                {
                                    "name": "5",
                                    "children": [
                                        {
                                            "name": "0",
                                            "children": [
                                                {
                                                    "name": "0",
                                                    "children": [
                                                        {
                                                            "name": "svg/svg/g/g_6/g_33/g_34/g_35/path_21",
                                                            "value": 1
                                                        }
                                                    ]
                                                }
                                            ]
                                        }
                                    ]
                                },
                                {
                                    "name": "6",
                                    "children": [
                                        {
                                            "name": "0",
                                            "children": [
                                                {
                                                    "name": "0",
                                                    "children": [
                                                        {
                                                            "name": "svg/svg/g/g_6/g_36/g_37/g_38/path_22",
                                                            "value": 1
                                                        }
                                                    ]
                                                }
                                            ]
                                        }
                                    ]
                                },
                                {
                                    "name": "7",
                                    "children": [
                                        {
                                            "name": "0",
                                            "children": [
                                                {
                                                    "name": "0",
                                                    "children": [
                                                        {
                                                            "name": "svg/svg/g/g_6/g_39/g_40/g_41/path_23",
                                                            "value": 1
                                                        }
                                                    ]
                                                },
                                                {
                                                    "name": "1",
                                                    "children": [
                                                        {
                                                            "name": "svg/svg/g/g_6/g_39/g_40/g_42/path_24",
                                                            "value": 1
                                                        }
                                                    ]
                                                },
                                                {
                                                    "name": "2",
                                                    "children": [
                                                        {
                                                            "name": "svg/svg/g/g_6/g_39/g_40/g_43/path_25",
                                                            "value": 1
                                                        }
                                                    ]
                                                },
                                                {
                                                    "name": "3",
                                                    "children": [
                                                        {
                                                            "name": "svg/svg/g/g_6/g_39/g_40/g_44/path_26",
                                                            "value": 1
                                                        }
                                                    ]
                                                },
                                                {
                                                    "name": "4",
                                                    "children": [
                                                        {
                                                            "name": "svg/svg/g/g_6/g_39/g_40/g_45/path_27",
                                                            "value": 1
                                                        }
                                                    ]
                                                },
                                                {
                                                    "name": "5",
                                                    "children": [
                                                        {
                                                            "name": "svg/svg/g/g_6/g_39/g_40/g_46/path_28",
                                                            "value": 1
                                                        }
                                                    ]
                                                },
                                                {
                                                    "name": "6",
                                                    "children": [
                                                        {
                                                            "name": "svg/svg/g/g_6/g_39/g_40/g_47/path_29",
                                                            "value": 1
                                                        }
                                                    ]
                                                },
                                                {
                                                    "name": "7",
                                                    "children": [
                                                        {
                                                            "name": "svg/svg/g/g_6/g_39/g_40/g_48/path_30",
                                                            "value": 1
                                                        }
                                                    ]
                                                },
                                                {
                                                    "name": "8",
                                                    "children": [
                                                        {
                                                            "name": "svg/svg/g/g_6/g_39/g_40/g_49/path_31",
                                                            "value": 1
                                                        }
                                                    ]
                                                },
                                                {
                                                    "name": "9",
                                                    "children": [
                                                        {
                                                            "name": "svg/svg/g/g_6/g_39/g_40/g_50/path_32",
                                                            "value": 1
                                                        }
                                                    ]
                                                },
                                                {
                                                    "name": "10",
                                                    "children": [
                                                        {
                                                            "name": "svg/svg/g/g_6/g_39/g_40/g_51/path_33",
                                                            "value": 1
                                                        }
                                                    ]
                                                },
                                                {
                                                    "name": "11",
                                                    "children": [
                                                        {
                                                            "name": "svg/svg/g/g_6/g_39/g_40/g_52/path_34",
                                                            "value": 1
                                                        }
                                                    ]
                                                },
                                                {
                                                    "name": "12",
                                                    "children": [
                                                        {
                                                            "name": "svg/svg/g/g_6/g_39/g_40/g_53/path_35",
                                                            "value": 1
                                                        }
                                                    ]
                                                },
                                                {
                                                    "name": "13",
                                                    "children": [
                                                        {
                                                            "name": "svg/svg/g/g_6/g_39/g_40/g_54/path_36",
                                                            "value": 1
                                                        }
                                                    ]
                                                },
                                                {
                                                    "name": "14",
                                                    "children": [
                                                        {
                                                            "name": "svg/svg/g/g_6/g_39/g_40/g_55/path_37",
                                                            "value": 1
                                                        }
                                                    ]
                                                },
                                                {
                                                    "name": "15",
                                                    "children": [
                                                        {
                                                            "name": "svg/svg/g/g_6/g_39/g_40/g_56/path_38",
                                                            "value": 1
                                                        }
                                                    ]
                                                },
                                                {
                                                    "name": "16",
                                                    "children": [
                                                        {
                                                            "name": "svg/svg/g/g_6/g_39/g_40/g_57/path_39",
                                                            "value": 1
                                                        }
                                                    ]
                                                },
                                                {
                                                    "name": "17",
                                                    "children": [
                                                        {
                                                            "name": "svg/svg/g/g_6/g_39/g_40/g_58/path_40",
                                                            "value": 1
                                                        }
                                                    ]
                                                },
                                                {
                                                    "name": "18",
                                                    "children": [
                                                        {
                                                            "name": "svg/svg/g/g_6/g_39/g_40/g_59/path_41",
                                                            "value": 1
                                                        }
                                                    ]
                                                },
                                                {
                                                    "name": "19",
                                                    "children": [
                                                        {
                                                            "name": "svg/svg/g/g_6/g_39/g_40/g_60/path_42",
                                                            "value": 1
                                                        },
                                                        {
                                                            "name": "svg/svg/g/g_6/g_39/g_40/g_60/path_43",
                                                            "value": 1
                                                        }
                                                    ]
                                                }
                                            ]
                                        }
                                    ]
                                }
                            ]
                        },
                        {
                            "name": "7",
                            "children": [
                                {
                                    "name": "svg/svg/g/g_61/line_2",
                                    "value": 1
                                },
                                {
                                    "name": "svg/svg/g/g_61/line_3",
                                    "value": 1
                                }
                            ]
                        },
                        {
                            "name": "8",
                            "children": [
                                {
                                    "name": "svg/svg/g/g_62/line_4",
                                    "value": 1
                                },
                                {
                                    "name": "svg/svg/g/g_62/line_5",
                                    "value": 1
                                },
                                {
                                    "name": "3",
                                    "children": [
                                        {
                                            "name": "svg/svg/g/g_62/g_64/line_6",
                                            "value": 1
                                        },
                                        {
                                            "name": "svg/svg/g/g_62/g_64/line_7",
                                            "value": 1
                                        },
                                        {
                                            "name": "svg/svg/g/g_62/g_64/line_8",
                                            "value": 1
                                        },
                                        {
                                            "name": "svg/svg/g/g_62/g_64/line_9",
                                            "value": 1
                                        },
                                        {
                                            "name": "svg/svg/g/g_62/g_64/line_10",
                                            "value": 1
                                        },
                                        {
                                            "name": "svg/svg/g/g_62/g_64/line_11",
                                            "value": 1
                                        },
                                        {
                                            "name": "svg/svg/g/g_62/g_64/line_12",
                                            "value": 1
                                        }
                                    ]
                                }
                            ]
                        },
                        {
                            "name": "svg/svg/g/line_13",
                            "value": 1
                        },
                        {
                            "name": "svg/svg/g/line_14",
                            "value": 1
                        },
                        {
                            "name": "svg/svg/g/line_15",
                            "value": 1
                        },
                        {
                            "name": "svg/svg/g/line_16",
                            "value": 1
                        },
                        {
                            "name": "svg/svg/g/line_17",
                            "value": 1
                        },
                        {
                            "name": "svg/svg/g/line_18",
                            "value": 1
                        },
                        {
                            "name": "svg/svg/g/line_19",
                            "value": 1
                        },
                        {
                            "name": "svg/svg/g/line_20",
                            "value": 1
                        },
                        {
                            "name": "svg/svg/g/line_21",
                            "value": 1
                        },
                        {
                            "name": "svg/svg/g/line_22",
                            "value": 1
                        },
                        {
                            "name": "svg/svg/g/line_23",
                            "value": 1
                        },
                        {
                            "name": "svg/svg/g/line_24",
                            "value": 1
                        },
                        {
                            "name": "svg/svg/g/line_25",
                            "value": 1
                        },
                        {
                            "name": "svg/svg/g/rect_2",
                            "value": 1
                        },
                        {
                            "name": "23",
                            "children": [
                                {
                                    "name": "2",
                                    "children": [
                                        {
                                            "name": "svg/svg/g/defs/clipPath_2/rect_3",
                                            "value": 1
                                        }
                                    ]
                                },
                                {
                                    "name": "3",
                                    "children": [
                                        {
                                            "name": "svg/svg/g/defs/clipPath_3/rect_4",
                                            "value": 1
                                        }
                                    ]
                                },
                                {
                                    "name": "4",
                                    "children": [
                                        {
                                            "name": "svg/svg/g/defs/clipPath_4/rect_5",
                                            "value": 1
                                        }
                                    ]
                                }
                            ]
                        }
                    ]
                },
                {
                    "name": "3",
                    "children": [
                        {
                            "name": "svg/svg/g_65/text_13",
                            "value": 1
                        },
                        {
                            "name": "svg/svg/g_65/text_14",
                            "value": 1
                        },
                        {
                            "name": "svg/svg/g_65/text_15",
                            "value": 1
                        },
                        {
                            "name": "svg/svg/g_65/text_16",
                            "value": 1
                        },
                        {
                            "name": "svg/svg/g_65/text_17",
                            "value": 1
                        },
                        {
                            "name": "svg/svg/g_65/text_18",
                            "value": 1
                        },
                        {
                            "name": "svg/svg/g_65/text_19",
                            "value": 1
                        },
                        {
                            "name": "svg/svg/g_65/text_20",
                            "value": 1
                        }
                    ]
                }
            ]
        }
    ]
}