{
    "name": "flare",
    "children": [
        {
            "name": "0",
            "children": [
                {
                    "name": "svg/svg/text",
                    "value": 1
                },
                {
                    "name": "3",
                    "children": [
                        {
                            "name": "svg/svg/g_2/rect",
                            "value": 1
                        }
                    ]
                },
                {
                    "name": "4",
                    "children": [
                        {
                            "name": "0",
                            "children": [
                                {
                                    "name": "svg/svg/g_5/g_6/text_1",
                                    "value": 1
                                }
                            ]
                        },
                        {
                            "name": "1",
                            "children": [
                                {
                                    "name": "svg/svg/g_5/g_7/text_2",
                                    "value": 1
                                }
                            ]
                        },
                        {
                            "name": "2",
                            "children": [
                                {
                                    "name": "svg/svg/g_5/g_8/text_3",
                                    "value": 1
                                }
                            ]
                        },
                        {
                            "name": "3",
                            "children": [
                                {
                                    "name": "svg/svg/g_5/g_9/text_4",
                                    "value": 1
                                }
                            ]
                        },
                        {
                            "name": "4",
                            "children": [
                                {
                                    "name": "svg/svg/g_5/g_10/text_5",
                                    "value": 1
                                }
                            ]
                        },
                        {
                            "name": "5",
                            "children": [
                                {
                                    "name": "svg/svg/g_5/g_11/text_6",
                                    "value": 1
                                }
                            ]
                        },
                        {
                            "name": "6",
                            "children": [
                                {
                                    "name": "svg/svg/g_5/g_12/text_7",
                                    "value": 1
                                }
                            ]
                        },
                        {
                            "name": "7",
                            "children": [
                                {
                                    "name": "svg/svg/g_5/g_13/text_8",
                                    "value": 1
                                }
                            ]
                        },
                        {
                            "name": "8",
                            "children": [
                                {
                                    "name": "svg/svg/g_5/g_14/text_9",
                                    "value": 1
                                }
                            ]
                        },
                        {
                            "name": "9",
                            "children": [
                                {
                                    "name": "svg/svg/g_5/g_15/text_10",
                                    "value": 1
                                }
                            ]
                        },
                        {
                            "name": "10",
                            "children": [
                                {
                                    "name": "svg/svg/g_5/g_16/text_11",
                                    "value": 1
                                }
                            ]
                        },
                        {
                            "name": "11",
                            "children": [
                                {
                                    "name": "svg/svg/g_5/g_17/text_12",
                                    "value": 1
                                }
                            ]
                        },
                        {
                            "name": "12",
                            "children": [
                                {
                                    "name": "svg/svg/g_5/g_18/text_13",
                                    "value": 1
                                }
                            ]
                        },
                        {
                            "name": "13",
                            "children": [
                                {
                                    "name": "svg/svg/g_5/g_19/text_14",
                                    "value": 1
                                }
                            ]
                        },
                        {
                            "name": "14",
                            "children": [
                                {
                                    "name": "svg/svg/g_5/g_20/text_15",
                                    "value": 1
                                }
                            ]
                        },
                        {
                            "name": "15",
                            "children": [
                                {
                                    "name": "svg/svg/g_5/g_21/text_16",
                                    "value": 1
                                }
                            ]
                        }
                    ]
                },
                {
                    "name": "svg/svg/text_17",
                    "value": 1
                },
                {
                    "name": "svg/svg/text_18",
                    "value": 1
                },
                {
                    "name": "6",
                    "children": [
                        {
                            "name": "svg/svg/text_18/a",
                            "value": 1
                        }
                    ]
                },
                {
                    "name": "svg/svg/text_19",
                    "value": 1
                },
                {
                    "name": "8",
                    "children": [
                        {
                            "name": "1",
                            "children": [
                                {
                                    "name": "0",
                                    "children": [
                                        {
                                            "name": "svg/svg/g_22/g_24/g_25/rect_1",
                                            "value": 1
                                        },
                                        {
                                            "name": "svg/svg/g_22/g_24/g_25/rect_2",
                                            "value": 1
                                        },
                                        {
                                            "name": "svg/svg/g_22/g_24/g_25/rect_3",
                                            "value": 1
                                        },
                                        {
                                            "name": "svg/svg/g_22/g_24/g_25/rect_4",
                                            "value": 1
                                        },
                                        {
                                            "name": "svg/svg/g_22/g_24/g_25/rect_5",
                                            "value": 1
                                        }
                                    ]
                                },
                                {
                                    "name": "1",
                                    "children": [
                                        {
                                            "name": "svg/svg/g_22/g_24/g_26/rect_6",
                                            "value": 1
                                        },
                                        {
                                            "name": "svg/svg/g_22/g_24/g_26/rect_7",
                                            "value": 1
                                        },
                                        {
                                            "name": "svg/svg/g_22/g_24/g_26/rect_8",
                                            "value": 1
                                        },
                                        {
                                            "name": "svg/svg/g_22/g_24/g_26/rect_9",
                                            "value": 1
                                        },
                                        {
                                            "name": "svg/svg/g_22/g_24/g_26/rect_10",
                                            "value": 1
                                        },
                                        {
                                            "name": "svg/svg/g_22/g_24/g_26/rect_11",
                                            "value": 1
                                        },
                                        {
                                            "name": "svg/svg/g_22/g_24/g_26/rect_12",
                                            "value": 1
                                        },
                                        {
                                            "name": "svg/svg/g_22/g_24/g_26/rect_13",
                                            "value": 1
                                        },
                                        {
                                            "name": "svg/svg/g_22/g_24/g_26/rect_14",
                                            "value": 1
                                        },
                                        {
                                            "name": "svg/svg/g_22/g_24/g_26/rect_15",
                                            "value": 1
                                        },
                                        {
                                            "name": "svg/svg/g_22/g_24/g_26/rect_16",
                                            "value": 1
                                        }
                                    ]
                                }
                            ]
                        }
                    ]
                },
                {
                    "name": "9",
                    "children": [
                        {
                            "name": "svg/svg/g_27/path",
                            "value": 1
                        }
                    ]
                },
                {
                    "name": "10",
                    "children": [
                        {
                            "name": "svg/svg/g_28/path_1",
                            "value": 1
                        }
                    ]
                },
                {
                    "name": "svg/svg/rect_17",
                    "value": 1
                },
                {
                    "name": "svg/svg/rect_18",
                    "value": 1
                },
                {
                    "name": "svg/svg/rect_19",
                    "value": 1
                },
                {
                    "name": "16",
                    "children": [
                        {
                            "name": "0",
                            "children": [
                                {
                                    "name": "svg/svg/defs/clipPath/rect_20",
                                    "value": 1
                                }
                            ]
                        },
                        {
                            "name": "svg/svg/defs/filter",
                            "value": 1
                        },
                        {
                            "name": "1",
                            "children": [
                                {
                                    "name": "svg/svg/defs/filter/fedropshadow",
                                    "value": 1
                                }
                            ]
                        }
                    ]
                },
                {
                    "name": "svg/svg/desc",
                    "value": 1
                }
            ]
        }
    ]
}